boto3_batch_utils/Base.py
boto3_batch_utils/Cloudwatch.py
boto3_batch_utils/Dynamodb.py
boto3_batch_utils/Kinesis.py
boto3_batch_utils/SQS.py
boto3_batch_utils/__init__.py
boto3_batch_utils/constants.py
boto3_batch_utils/utils.py
boto3_batch_utils-5.1.0.dist-info/LICENSE
boto3_batch_utils-5.1.0.dist-info/METADATA
boto3_batch_utils-5.1.0.dist-info/WHEEL
boto3_batch_utils-5.1.0.dist-info/top_level.txt
boto3_batch_utils-5.1.0.dist-info/RECORD
