Metadata-Version: 2.1
Name: boto3-batch-utils
Version: 5.1.0
Summary: A Client for managing batch interactions with AWS services
Home-page: https://g-farrow.github.io/boto3_batch_utils/
Author: Greg Farrow
Author-email: greg.farrow1@gmail.com
License: GNU APGL v3
Keywords: aws boto3 kinesis dynamo dynamodb sqs fifo batch
Platform: UNKNOWN
Requires-Dist: boto3 (>=1.11.13)
